audio_silence_marks/__init__.py
audio_silence_marks/__main__.py
audio_silence_marks/cli.py
audio_silence_marks/main.py
audio_silence_marks/targets/__init__.py
audio_silence_marks/targets/audipo.py
audio_silence_marks/types.py
audio_silence_marks-0.1.3.dist-info/entry_points.txt
audio_silence_marks-0.1.3.dist-info/LICENSE
audio_silence_marks-0.1.3.dist-info/WHEEL
audio_silence_marks-0.1.3.dist-info/METADATA
audio_silence_marks-0.1.3.dist-info/RECORD
