Metadata-Version: 2.1
Name: audio-silence-marks
Version: 0.1.3
Summary: Tool for creating silence marks for audio files
Home-page: https://github.com/OnkelTem/audio_silence_marks
License: MIT
Author: OnkelTem
Author-email: aneganov@gmail.com
Requires-Python: >=3.6,<4.0
Classifier: License :: OSI Approved :: MIT License
Classifier: Operating System :: OS Independent
Classifier: Programming Language :: Python :: 3
Classifier: Programming Language :: Python :: 3.6
Classifier: Programming Language :: Python :: 3.7
Classifier: Programming Language :: Python :: 3.8
Classifier: Programming Language :: Python :: 3.9
Requires-Dist: importlib-metadata (>=1.0,<2.0); python_version < "3.8"
Requires-Dist: typer (>=0.3.2,<0.4.0)
Project-URL: Repository, https://github.com/OnkelTem/audio_silence_marks
